insprdcli/__init__.py
insprdcli/main.py
insprdcli/controllers/__init__.py
insprdcli/controllers/base.py
insprdcli/core/__init__.py
insprdcli/core/exc.py
insprdcli/core/version.py
insprdcli/ext/__init__.py
insprdcli/plugins/__init__.py
insprdcli/templates/__init__.py
insprdcli/templates/command1.jinja2
insprdcli-0.0.1.dist-info/LICENSE.md
insprdcli-0.0.1.dist-info/METADATA
insprdcli-0.0.1.dist-info/WHEEL
insprdcli-0.0.1.dist-info/entry_points.txt
insprdcli-0.0.1.dist-info/top_level.txt
insprdcli-0.0.1.dist-info/RECORD
