Metadata-Version: 2.1
Name: insprdcli
Version: 0.0.1
Summary: Command-line interface into Inspired Platform
Home-page: https://github.com/InspiredMember/inspired-cli
Author: Jeff Trudeau
Author-email: jeff.trudeau@gmail.com
License: MIT
Platform: UNKNOWN
